README.rst
setup.cfg
setup.py
couchbase_stress_test/__init__.py
couchbase_stress_testing.egg-info/PKG-INFO
couchbase_stress_testing.egg-info/SOURCES.txt
couchbase_stress_testing.egg-info/dependency_links.txt
couchbase_stress_testing.egg-info/entry_points.txt
couchbase_stress_testing.egg-info/requires.txt
couchbase_stress_testing.egg-info/top_level.txt