Metadata-Version: 1.1
Name: couchbase-stress-testing
Version: 1.0.0
Summary: Couchbase stress test
Home-page: https://github.com/Travix-International/couchbase-stress-testing
Author: Travix Internationals
Author-email: malsharbaji@travix.com
License: MIT
Keywords: couchbase stress testing
Platform: UNKNOWN
Classifier: Development Status :: 3 - Alpha
Classifier: Environment :: Web Environment
Classifier: Intended Audience :: Developers
Classifier: License :: OSI Approved :: MIT License
Classifier: Programming Language :: Python :: 2
Classifier: Programming Language :: Python :: 2.7
Classifier: Programming Language :: Python :: 3
Classifier: Programming Language :: Python :: 3.5
Classifier: Programming Language :: Python :: 3.6
Classifier: Programming Language :: Python :: 3.7
